{"name":"Auth","tagline":"表单验证组件","body":"# Auth\r\n\r\nAuth是非常强大的表单校验组件，Auth在灵活性上是无与伦比，足以满足大部分的表单场景。\r\n\r\nAuth支持异步校验，支持与异步上传组件配合使用。\r\n\r\n作者：张挺（V1.4+）| 明河（V1.5+）\r\n\r\nv1.4.1发布，支持kissy1.2+ 欢迎试用反馈bug~~~\r\n\r\n## changelog\r\n\r\n### V1.6.1\r\n\r\n    [!] 修正add，无法显示消息的问题\r\n\r\n### V1.4.1 by 张挺\r\n\r\n    [+] 异步校验支持\r\n    [!] 优化部分代码\r\n\r\n### V1.6 by 明河\r\n\r\n    [!] 基于kissy1.4\r\n    [!] 消息改成插件\r\n    [!]模块优化\r\n    [!]可以配置消息层模版\r\n    [!]增加fnWrapper配置\r\n    [!]Auth新增fnFilter配置\r\n    [!]Auth新增fnConfig配置\r\n    [!]优化异步链\r\n\r\n### V1.5 by 明河\r\n\r\n    [!] 重构消息类\r\n    [!] 改用get和set来获取/设置属性\r\n    [!] tag config方式更改\r\n    [!] [Auth] 优先获取name，而不是id\r\n    [!] [Field] el配置改成target\r\n    [!] [Field] 修改event配置\r\n    [!] [Field] validate()方法去掉cfg参数，多个规则逗号隔开\r\n    [!] [Field] 遍历时排除button元素\r\n    [!] [Rule] 重构\r\n    [!] [Rule]equalTo改成equal\r\n    [!] [ruleFactory] 颠倒规则函数的value和pv\r\n    [!] [ruleFactory] 不再区分html规则和自定义规则\r\n    [!] [ruleFactory] 默认规则提取成default.js\r\n    [!] [Msg] 重构\r\n    [!] [Msg] msg传递方式优化\r\n    [!] [Msg] show()方法改变\r\n    [!] 去掉多余无用的样式，使用stylus改写\r\n    [!] [Field]修正不存在验证规则时报错的bug\r\n\r\n    [+] 新增render()，不再new时马上初始化逻辑\r\n    [+] 增加validate的同名方法test\r\n    [+] 继承promise\r\n    [+] 异步校验支持\r\n    [+] 增加对uploader的支持\r\n\r\n    [+] [auth]增加rules属性，用于获取所有的验证规则\r\n    [+] [auth]增加useId属性，可以强制使用id作为字段标识\r\n    [+] [auth]增加submitTest配置，用于拦截表单提交，先触发验证\r\n    [+] [auth]增加fields属性，所有的字段\r\n    [+] [auth]验证前过滤掉不需要验证的字段\r\n    [+] [auth]test()支持指定需要验证的字段，比如test(\"user,email\")\r\n    [+] [auth]增加fieldTarget方法\r\n    [+] [auth]增加field方法\r\n    [+] [auth]增加success、error事件\r\n    [+] [auth]error事件广播出出错的fields\r\n\r\n    [+] [Field]增加success、error、beforeTest事件\r\n    [+] [Filed]新增rules属性，用于获取所有的规则\r\n    [+] [Filed]新增exclude配置，用于排除指定规则验证\r\n    [+] [Filed]新增host属性\r\n    [+] [Filed]将Field实例缓存到元素的data-field\r\n    [+] [Filed]增加name属性\r\n    [+] [Filed]增加rule方法\r\n\r\n    [+] [ruleFactory] 支持批量添加验证规则\r\n    [+] [Rule]规则可以设置默认消息\r\n    [+] [Rule]required组的处理\r\n    [+] [Rule]required清理掉空格\r\n    [+] [Rule]max和min可以处理checkbox的情况\r\n    [+] [Rule]增加mobile、email、date、number支持\r\n    [+] [Rule]新增equal-field规则\r\n\r\n    [+] [Msg]兼容服务器返回的错误信息\r\n    [+] [Msg]可以传自定义消息类进去\r\n    [+] [Msg]可以自动生成消息层\r\n    [+] [Msg]默认规则增加msg\r\n\r\n    [-] 删除rule/base\r\n    [-] 删除propertyRule\r\n    [-] 删除lib/base\r\n\r\n### V1.4\r\n\r\n    [!] 从butterfly中迁移到新的gallery","google":"","note":"Don't delete this file! It's used internally to help with page regeneration."}